pickleshare.py
pickleshare-0.7.2.dist-info/DESCRIPTION.rst
pickleshare-0.7.2.dist-info/METADATA
pickleshare-0.7.2.dist-info/RECORD
pickleshare-0.7.2.dist-info/WHEEL
pickleshare-0.7.2.dist-info/metadata.json
pickleshare-0.7.2.dist-info/top_level.txt
