Metadata-Version: 1.1
Name: pickleshare
Version: 0.7.2
Summary: Tiny 'shelve'-like database with concurrency support
Home-page: https://github.com/pickleshare/pickleshare
Author: Ville Vainio
Author-email: vivainio@gmail.com
License: MIT
Keywords: database persistence pickle ipc shelve
Platform: UNKNOWN
Classifier: License :: OSI Approved :: MIT License
Classifier: Programming Language :: Python :: 2
Classifier: Programming Language :: Python :: 2.7
Classifier: Programming Language :: Python :: 3
